{
  "generatedAt": "2025-10-13T09:05:48.056Z",
  "weeklyData": [
    {
      "date": "2025-10-07",
      "gradeKey": "grade1",
      "quantityKg": 217.24,
      "unitPriceWon": 345243.25
    },
    {
      "date": "2025-10-07",
      "gradeKey": "grade2",
      "quantityKg": 504.49,
      "unitPriceWon": 265318.66
    },
    {
      "date": "2025-10-07",
      "gradeKey": "grade3Stopped",
      "quantityKg": 943.59,
      "unitPriceWon": 201693.4
    },
    {
      "date": "2025-10-07",
      "gradeKey": "grade3Estimated",
      "quantityKg": 2327.89,
      "unitPriceWon": 176455.6
    },
    {
      "date": "2025-10-07",
      "gradeKey": "gradeBelow",
      "quantityKg": 3035.04,
      "unitPriceWon": 126285.88
    },
    {
      "date": "2025-10-07",
      "gradeKey": "mixedGrade",
      "quantityKg": 61.7,
      "unitPriceWon": 85829.95
    },
    {
      "date": "2025-10-08",
      "gradeKey": "grade1",
      "quantityKg": 235.83,
      "unitPriceWon": 323130.41
    },
    {
      "date": "2025-10-08",
      "gradeKey": "grade2",
      "quantityKg": 525.38,
      "unitPriceWon": 245351.95
    },
    {
      "date": "2025-10-08",
      "gradeKey": "grade3Stopped",
      "quantityKg": 1032.92,
      "unitPriceWon": 188969.23
    },
    {
      "date": "2025-10-08",
      "gradeKey": "grade3Estimated",
      "quantityKg": 3063.51,
      "unitPriceWon": 148592.85
    },
    {
      "date": "2025-10-08",
      "gradeKey": "gradeBelow",
      "quantityKg": 3780.02,
      "unitPriceWon": 115278.84
    },
    {
      "date": "2025-10-08",
      "gradeKey": "mixedGrade",
      "quantityKg": 304.47,
      "unitPriceWon": 75328.03
    },
    {
      "date": "2025-10-09",
      "gradeKey": "grade1",
      "quantityKg": 202.31,
      "unitPriceWon": 358190.16
    },
    {
      "date": "2025-10-09",
      "gradeKey": "grade2",
      "quantityKg": 372.58,
      "unitPriceWon": 274975.73
    },
    {
      "date": "2025-10-09",
      "gradeKey": "grade3Stopped",
      "quantityKg": 691.21,
      "unitPriceWon": 217105.71
    },
    {
      "date": "2025-10-09",
      "gradeKey": "grade3Estimated",
      "quantityKg": 2272.56,
      "unitPriceWon": 175042.92
    },
    {
      "date": "2025-10-09",
      "gradeKey": "gradeBelow",
      "quantityKg": 2476.23,
      "unitPriceWon": 137670.99
    },
    {
      "date": "2025-10-09",
      "gradeKey": "mixedGrade",
      "quantityKg": 343.39,
      "unitPriceWon": 85413.79
    },
    {
      "date": "2025-10-10",
      "gradeKey": "grade1",
      "quantityKg": 172.7,
      "unitPriceWon": 421844.58
    },
    {
      "date": "2025-10-10",
      "gradeKey": "grade2",
      "quantityKg": 373.32,
      "unitPriceWon": 315923.38
    },
    {
      "date": "2025-10-10",
      "gradeKey": "grade3Stopped",
      "quantityKg": 511.14,
      "unitPriceWon": 248987.61
    },
    {
      "date": "2025-10-10",
      "gradeKey": "grade3Estimated",
      "quantityKg": 1927.39,
      "unitPriceWon": 206016.8
    },
    {
      "date": "2025-10-10",
      "gradeKey": "gradeBelow",
      "quantityKg": 2140.57,
      "unitPriceWon": 160400.34
    },
    {
      "date": "2025-10-10",
      "gradeKey": "mixedGrade",
      "quantityKg": 252.41,
      "unitPriceWon": 110431.66
    },
    {
      "date": "2025-10-11",
      "gradeKey": "grade1",
      "quantityKg": 192.97,
      "unitPriceWon": 455035.94
    },
    {
      "date": "2025-10-11",
      "gradeKey": "grade2",
      "quantityKg": 430.91,
      "unitPriceWon": 303855.38
    },
    {
      "date": "2025-10-11",
      "gradeKey": "grade3Stopped",
      "quantityKg": 544.25,
      "unitPriceWon": 251536.42
    },
    {
      "date": "2025-10-11",
      "gradeKey": "grade3Estimated",
      "quantityKg": 2238.23,
      "unitPriceWon": 205570.07
    },
    {
      "date": "2025-10-11",
      "gradeKey": "gradeBelow",
      "quantityKg": 2780.06,
      "unitPriceWon": 159425.4
    },
    {
      "date": "2025-10-11",
      "gradeKey": "mixedGrade",
      "quantityKg": 354.21,
      "unitPriceWon": 120521.06
    },
    {
      "date": "2025-10-12",
      "gradeKey": "grade1",
      "quantityKg": 171.28,
      "unitPriceWon": 459472.75
    },
    {
      "date": "2025-10-12",
      "gradeKey": "grade2",
      "quantityKg": 320.15,
      "unitPriceWon": 321917.33
    },
    {
      "date": "2025-10-12",
      "gradeKey": "grade3Stopped",
      "quantityKg": 448.81,
      "unitPriceWon": 254511.37
    },
    {
      "date": "2025-10-12",
      "gradeKey": "grade3Estimated",
      "quantityKg": 1955.38,
      "unitPriceWon": 199424.52
    },
    {
      "date": "2025-10-12",
      "gradeKey": "gradeBelow",
      "quantityKg": 2800.77,
      "unitPriceWon": 146319.28
    },
    {
      "date": "2025-10-12",
      "gradeKey": "mixedGrade",
      "quantityKg": 371.74,
      "unitPriceWon": 116953.49
    },
    {
      "date": "2025-10-13",
      "gradeKey": "grade1",
      "quantityKg": 127.05,
      "unitPriceWon": 478280.73
    },
    {
      "date": "2025-10-13",
      "gradeKey": "grade2",
      "quantityKg": 236.75,
      "unitPriceWon": 344905.42
    },
    {
      "date": "2025-10-13",
      "gradeKey": "grade3Stopped",
      "quantityKg": 366.32,
      "unitPriceWon": 252376.59
    },
    {
      "date": "2025-10-13",
      "gradeKey": "grade3Estimated",
      "quantityKg": 1452.91,
      "unitPriceWon": 182705.99
    },
    {
      "date": "2025-10-13",
      "gradeKey": "gradeBelow",
      "quantityKg": 2131.18,
      "unitPriceWon": 133348.08
    },
    {
      "date": "2025-10-13",
      "gradeKey": "mixedGrade",
      "quantityKg": 482.12,
      "unitPriceWon": 95279.9
    }
  ]
}