[
  {
    "region": "강원",
    "union": "홍천",
    "date": "2022-9-27",
    "lastUpdated": "2022-09-27 17:43:48.0",
    "auctionQuantity": {
      "untilYesterday": "3,398.55kg",
      "today": "65.29kg",
      "total": "3,463.84kg"
    },
    "auctionAmount": {
      "untilYesterday": "676,666,520원",
      "today": "10,542,300원",
      "total": "687,208,820원"
    },
    "grade1": {
      "quantity": "0.95kg",
      "unitPrice": "300,000원"
    },
    "grade2": {
      "quantity": "1.8kg",
      "unitPrice": "250,000원"
    },
    "grade3Stopped": {
      "quantity": "1.85kg",
      "unitPrice": "200,000원"
    },
    "grade3Estimated": {
      "quantity": "16.69kg",
      "unitPrice": "170,000원"
    },
    "gradeBelow": {
      "quantity": "44kg",
      "unitPrice": "150,000원"
    },
    "mixedGrade": {
      "quantity": "0kg",
      "unitPrice": "0원"
    }
  },
  {
    "region": "강원",
    "union": "양구",
    "date": "2022-9-27",
    "lastUpdated": "2022-09-26 17:22:46.0",
    "auctionQuantity": {
      "untilYesterday": "1,295.71kg",
      "today": "0kg",
      "total": "1,295.71kg"
    },
    "auctionAmount": {
      "untilYesterday": "232,317,615.4원",
      "today": "0원",
      "total": "232,317,615.4원"
    },
    "grade1": {
      "quantity": "0kg",
      "unitPrice": "0원"
    },
    "grade2": {
      "quantity": "0kg",
      "unitPrice": "0원"
    },
    "grade3Stopped": {
      "quantity": "0kg",
      "unitPrice": "0원"
    },
    "grade3Estimated": {
      "quantity": "0kg",
      "unitPrice": "0원"
    },
    "gradeBelow": {
      "quantity": "0kg",
      "unitPrice": "0원"
    },
    "mixedGrade": {
      "quantity": "0kg",
      "unitPrice": "0원"
    }
  },
  {
    "region": "강원",
    "union": "인제",
    "date": "2022-9-27",
    "lastUpdated": "2022-09-24 17:06:21.0",
    "auctionQuantity": {
      "untilYesterday": "4,112.36kg",
      "today": "0kg",
      "total": "4,112.36kg"
    },
    "auctionAmount": {
      "untilYesterday": "840,979,040.4원",
      "today": "0원",
      "total": "840,979,040.4원"
    },
    "grade1": {
      "quantity": "0kg",
      "unitPrice": "0원"
    },
    "grade2": {
      "quantity": "0kg",
      "unitPrice": "0원"
    },
    "grade3Stopped": {
      "quantity": "0kg",
      "unitPrice": "0원"
    },
    "grade3Estimated": {
      "quantity": "0kg",
      "unitPrice": "0원"
    },
    "gradeBelow": {
      "quantity": "0kg",
      "unitPrice": "0원"
    },
    "mixedGrade": {
      "quantity": "0kg",
      "unitPrice": "0원"
    }
  },
  {
    "region": "강원",
    "union": "고성",
    "date": "2022-9-27",
    "lastUpdated": "2022-09-27 17:06:53.0",
    "auctionQuantity": {
      "untilYesterday": "2,253.48kg",
      "today": "22.15kg",
      "total": "2,275.63kg"
    },
    "auctionAmount": {
      "untilYesterday": "559,663,756원",
      "today": "6,664,155원",
      "total": "566,327,911원"
    },
    "grade1": {
      "quantity": "0.42kg",
      "unitPrice": "723,000원"
    },
    "grade2": {
      "quantity": "0.47kg",
      "unitPrice": "587,700원"
    },
    "grade3Stopped": {
      "quantity": "0.88kg",
      "unitPrice": "437,700원"
    },
    "grade3Estimated": {
      "quantity": "4.65kg",
      "unitPrice": "363,000원"
    },
    "gradeBelow": {
      "quantity": "15.73kg",
      "unitPrice": "255,000원"
    },
    "mixedGrade": {
      "quantity": "0kg",
      "unitPrice": "0원"
    }
  },
  {
    "region": "강원",
    "union": "양양",
    "date": "2022-9-27",
    "lastUpdated": "2022-09-27 18:20:53.0",
    "auctionQuantity": {
      "untilYesterday": "4,517.12kg",
      "today": "67.79kg",
      "total": "4,584.91kg"
    },
    "auctionAmount": {
      "untilYesterday": "1,289,725,938.3원",
      "today": "26,016,799원",
      "total": "1,315,742,737.3원"
    },
    "grade1": {
      "quantity": "2.44kg",
      "unitPrice": "1,233,300원"
    },
    "grade2": {
      "quantity": "1.27kg",
      "unitPrice": "811,000원"
    },
    "grade3Stopped": {
      "quantity": "1.33kg",
      "unitPrice": "653,100원"
    },
    "grade3Estimated": {
      "quantity": "11.84kg",
      "unitPrice": "531,600원"
    },
    "gradeBelow": {
      "quantity": "50.91kg",
      "unitPrice": "291,000원"
    },
    "mixedGrade": {
      "quantity": "0kg",
      "unitPrice": "0원"
    }
  },
  {
    "region": "강원",
    "union": "강릉",
    "date": "2022-9-27",
    "lastUpdated": "2022-09-27 16:52:46.0",
    "auctionQuantity": {
      "untilYesterday": "754.14kg",
      "today": "10.27kg",
      "total": "764.41kg"
    },
    "auctionAmount": {
      "untilYesterday": "162,932,443원",
      "today": "3,008,805원",
      "total": "165,941,248원"
    },
    "grade1": {
      "quantity": "0kg",
      "unitPrice": "0원"
    },
    "grade2": {
      "quantity": "0.05kg",
      "unitPrice": "498,000원"
    },
    "grade3Stopped": {
      "quantity": "0.19kg",
      "unitPrice": "290,000원"
    },
    "grade3Estimated": {
      "quantity": "2.3kg",
      "unitPrice": "371,000원"
    },
    "gradeBelow": {
      "quantity": "7.73kg",
      "unitPrice": "268,500원"
    },
    "mixedGrade": {
      "quantity": "0kg",
      "unitPrice": "0원"
    }
  },
  {
    "region": "강원",
    "union": "삼척",
    "date": "2022-9-27",
    "lastUpdated": "2022-09-27 17:16:01.0",
    "auctionQuantity": {
      "untilYesterday": "3,721.51kg",
      "today": "102.44kg",
      "total": "3,823.95kg"
    },
    "auctionAmount": {
      "untilYesterday": "871,558,129.6원",
      "today": "28,503,185원",
      "total": "900,061,314.6원"
    },
    "grade1": {
      "quantity": "0.61kg",
      "unitPrice": "710,000원"
    },
    "grade2": {
      "quantity": "2.06kg",
      "unitPrice": "651,000원"
    },
    "grade3Stopped": {
      "quantity": "3.44kg",
      "unitPrice": "471,000원"
    },
    "grade3Estimated": {
      "quantity": "26.79kg",
      "unitPrice": "354,500원"
    },
    "gradeBelow": {
      "quantity": "69.54kg",
      "unitPrice": "224,500원"
    },
    "mixedGrade": {
      "quantity": "0kg",
      "unitPrice": "0원"
    }
  },
  {
    "region": "경북",
    "union": "의성",
    "date": "2022-9-27",
    "lastUpdated": "2022-09-27 17:49:24.0",
    "auctionQuantity": {
      "untilYesterday": "491.5kg",
      "today": "10.18kg",
      "total": "501.68kg"
    },
    "auctionAmount": {
      "untilYesterday": "97,660,001원",
      "today": "1,682,172원",
      "total": "99,342,173원"
    },
    "grade1": {
      "quantity": "0kg",
      "unitPrice": "0원"
    },
    "grade2": {
      "quantity": "0kg",
      "unitPrice": "0원"
    },
    "grade3Stopped": {
      "quantity": "0kg",
      "unitPrice": "0원"
    },
    "grade3Estimated": {
      "quantity": "1.56kg",
      "unitPrice": "305,100원"
    },
    "gradeBelow": {
      "quantity": "3.48kg",
      "unitPrice": "193,300원"
    },
    "mixedGrade": {
      "quantity": "5.14kg",
      "unitPrice": "103,800원"
    }
  },
  {
    "region": "경북",
    "union": "안동",
    "date": "2022-9-27",
    "lastUpdated": "2022-09-27 17:04:08.0",
    "auctionQuantity": {
      "untilYesterday": "4,930.29kg",
      "today": "191.07kg",
      "total": "5,121.36kg"
    },
    "auctionAmount": {
      "untilYesterday": "1,056,242,329.2원",
      "today": "44,694,330원",
      "total": "1,100,936,659.2원"
    },
    "grade1": {
      "quantity": "0.6kg",
      "unitPrice": "660,000원"
    },
    "grade2": {
      "quantity": "2.69kg",
      "unitPrice": "650,000원"
    },
    "grade3Stopped": {
      "quantity": "3.33kg",
      "unitPrice": "475,000원"
    },
    "grade3Estimated": {
      "quantity": "20.83kg",
      "unitPrice": "350,000원"
    },
    "gradeBelow": {
      "quantity": "108.42kg",
      "unitPrice": "223,000원"
    },
    "mixedGrade": {
      "quantity": "55.2kg",
      "unitPrice": "172,100원"
    }
  },
  {
    "region": "경북",
    "union": "청송",
    "date": "2022-9-27",
    "lastUpdated": "2022-09-27 17:16:27.0",
    "auctionQuantity": {
      "untilYesterday": "4,093.02kg",
      "today": "154kg",
      "total": "4,247.02kg"
    },
    "auctionAmount": {
      "untilYesterday": "931,036,444원",
      "today": "43,061,560원",
      "total": "974,098,004원"
    },
    "grade1": {
      "quantity": "3.48kg",
      "unitPrice": "670,000원"
    },
    "grade2": {
      "quantity": "6.38kg",
      "unitPrice": "560,000원"
    },
    "grade3Stopped": {
      "quantity": "10.6kg",
      "unitPrice": "477,700원"
    },
    "grade3Estimated": {
      "quantity": "27.1kg",
      "unitPrice": "351,000원"
    },
    "gradeBelow": {
      "quantity": "65kg",
      "unitPrice": "235,200원"
    },
    "mixedGrade": {
      "quantity": "41.44kg",
      "unitPrice": "176,000원"
    }
  },
  {
    "region": "경북",
    "union": "영덕",
    "date": "2022-9-27",
    "lastUpdated": "2022-09-27 17:23:23.0",
    "auctionQuantity": {
      "untilYesterday": "6,898.33kg",
      "today": "653.16kg",
      "total": "7,551.49kg"
    },
    "auctionAmount": {
      "untilYesterday": "1,760,281,322.87원",
      "today": "185,480,762.44원",
      "total": "1,945,762,085.31원"
    },
    "grade1": {
      "quantity": "18.74kg",
      "unitPrice": "649,000원"
    },
    "grade2": {
      "quantity": "33.94kg",
      "unitPrice": "608,999원"
    },
    "grade3Stopped": {
      "quantity": "18.28kg",
      "unitPrice": "466,900원"
    },
    "grade3Estimated": {
      "quantity": "184.02kg",
      "unitPrice": "322,999원"
    },
    "gradeBelow": {
      "quantity": "313.44kg",
      "unitPrice": "228,110원"
    },
    "mixedGrade": {
      "quantity": "84.74kg",
      "unitPrice": "155,500원"
    }
  },
  {
    "region": "경북",
    "union": "청도",
    "date": "2022-9-27",
    "lastUpdated": "2022-09-27 16:58:14.0",
    "auctionQuantity": {
      "untilYesterday": "1,510.07kg",
      "today": "83.46kg",
      "total": "1,593.53kg"
    },
    "auctionAmount": {
      "untilYesterday": "356,085,063.76원",
      "today": "27,894,102.5원",
      "total": "383,979,166.26원"
    },
    "grade1": {
      "quantity": "0.11kg",
      "unitPrice": "730,000원"
    },
    "grade2": {
      "quantity": "0.94kg",
      "unitPrice": "666,000원"
    },
    "grade3Stopped": {
      "quantity": "1.34kg",
      "unitPrice": "556,000원"
    },
    "grade3Estimated": {
      "quantity": "24.82kg",
      "unitPrice": "388,000원"
    },
    "gradeBelow": {
      "quantity": "56.25kg",
      "unitPrice": "298,890원"
    },
    "mixedGrade": {
      "quantity": "0kg",
      "unitPrice": "0원"
    }
  },
  {
    "region": "경북",
    "union": "상주",
    "date": "2022-9-27",
    "lastUpdated": "2022-09-26 17:16:47.0",
    "auctionQuantity": {
      "untilYesterday": "1,530.14kg",
      "today": "0kg",
      "total": "1,530.14kg"
    },
    "auctionAmount": {
      "untilYesterday": "304,691,914원",
      "today": "0원",
      "total": "304,691,914원"
    },
    "grade1": {
      "quantity": "0kg",
      "unitPrice": "0원"
    },
    "grade2": {
      "quantity": "0kg",
      "unitPrice": "0원"
    },
    "grade3Stopped": {
      "quantity": "0kg",
      "unitPrice": "0원"
    },
    "grade3Estimated": {
      "quantity": "0kg",
      "unitPrice": "0원"
    },
    "gradeBelow": {
      "quantity": "0kg",
      "unitPrice": "0원"
    },
    "mixedGrade": {
      "quantity": "0kg",
      "unitPrice": "0원"
    }
  },
  {
    "region": "경북",
    "union": "문경",
    "date": "2022-9-27",
    "lastUpdated": "2022-09-27 17:18:19.0",
    "auctionQuantity": {
      "untilYesterday": "6,383.58kg",
      "today": "63.32kg",
      "total": "6,446.9kg"
    },
    "auctionAmount": {
      "untilYesterday": "1,261,312,895원",
      "today": "18,268,380원",
      "total": "1,279,581,275원"
    },
    "grade1": {
      "quantity": "0.08kg",
      "unitPrice": "1,500,000원"
    },
    "grade2": {
      "quantity": "0.4kg",
      "unitPrice": "520,000원"
    },
    "grade3Stopped": {
      "quantity": "0.24kg",
      "unitPrice": "472,000원"
    },
    "grade3Estimated": {
      "quantity": "4.4kg",
      "unitPrice": "436,600원"
    },
    "gradeBelow": {
      "quantity": "58.2kg",
      "unitPrice": "273,300원"
    },
    "mixedGrade": {
      "quantity": "0kg",
      "unitPrice": "0원"
    }
  },
  {
    "region": "경북",
    "union": "예천",
    "date": "2022-9-27",
    "lastUpdated": "2022-09-26 17:15:07.0",
    "auctionQuantity": {
      "untilYesterday": "987.18kg",
      "today": "0kg",
      "total": "987.18kg"
    },
    "auctionAmount": {
      "untilYesterday": "200,483,076원",
      "today": "0원",
      "total": "200,483,076원"
    },
    "grade1": {
      "quantity": "0kg",
      "unitPrice": "0원"
    },
    "grade2": {
      "quantity": "0kg",
      "unitPrice": "0원"
    },
    "grade3Stopped": {
      "quantity": "0kg",
      "unitPrice": "0원"
    },
    "grade3Estimated": {
      "quantity": "0kg",
      "unitPrice": "0원"
    },
    "gradeBelow": {
      "quantity": "0kg",
      "unitPrice": "0원"
    },
    "mixedGrade": {
      "quantity": "0kg",
      "unitPrice": "0원"
    }
  },
  {
    "region": "경북",
    "union": "영주",
    "date": "2022-9-27",
    "lastUpdated": "2022-09-27 16:55:24.0",
    "auctionQuantity": {
      "untilYesterday": "685.06kg",
      "today": "18.82kg",
      "total": "703.88kg"
    },
    "auctionAmount": {
      "untilYesterday": "152,865,452원",
      "today": "6,186,920원",
      "total": "159,052,372원"
    },
    "grade1": {
      "quantity": "0kg",
      "unitPrice": "0원"
    },
    "grade2": {
      "quantity": "0.38kg",
      "unitPrice": "575,000원"
    },
    "grade3Stopped": {
      "quantity": "0kg",
      "unitPrice": "0원"
    },
    "grade3Estimated": {
      "quantity": "3.56kg",
      "unitPrice": "420,500원"
    },
    "gradeBelow": {
      "quantity": "14.88kg",
      "unitPrice": "300,500원"
    },
    "mixedGrade": {
      "quantity": "0kg",
      "unitPrice": "0원"
    }
  },
  {
    "region": "경북",
    "union": "봉화",
    "date": "2022-9-27",
    "lastUpdated": "2022-09-27 16:52:43.0",
    "auctionQuantity": {
      "untilYesterday": "1,335.62kg",
      "today": "20.06kg",
      "total": "1,355.68kg"
    },
    "auctionAmount": {
      "untilYesterday": "303,458,903원",
      "today": "7,108,466원",
      "total": "310,567,369원"
    },
    "grade1": {
      "quantity": "0.92kg",
      "unitPrice": "710,000원"
    },
    "grade2": {
      "quantity": "1.44kg",
      "unitPrice": "655,900원"
    },
    "grade3Stopped": {
      "quantity": "0kg",
      "unitPrice": "0원"
    },
    "grade3Estimated": {
      "quantity": "4.3kg",
      "unitPrice": "405,900원"
    },
    "gradeBelow": {
      "quantity": "13.4kg",
      "unitPrice": "281,000원"
    },
    "mixedGrade": {
      "quantity": "0kg",
      "unitPrice": "0원"
    }
  },
  {
    "region": "경북",
    "union": "울진",
    "date": "2022-9-27",
    "lastUpdated": "2022-09-27 19:11:41.0",
    "auctionQuantity": {
      "untilYesterday": "1,816.6kg",
      "today": "196.25kg",
      "total": "2,012.85kg"
    },
    "auctionAmount": {
      "untilYesterday": "507,560,755.15원",
      "today": "61,282,325원",
      "total": "568,843,080.15원"
    },
    "grade1": {
      "quantity": "6.85kg",
      "unitPrice": "721,200원"
    },
    "grade2": {
      "quantity": "11.3kg",
      "unitPrice": "645,500원"
    },
    "grade3Stopped": {
      "quantity": "0kg",
      "unitPrice": "0원"
    },
    "grade3Estimated": {
      "quantity": "60.15kg",
      "unitPrice": "345,000원"
    },
    "gradeBelow": {
      "quantity": "117.95kg",
      "unitPrice": "239,900원"
    },
    "mixedGrade": {
      "quantity": "0kg",
      "unitPrice": "0원"
    }
  },
  {
    "region": "경남",
    "union": "거창",
    "date": "2022-9-27",
    "lastUpdated": "2022-09-27 17:06:37.0",
    "auctionQuantity": {
      "untilYesterday": "2,487.47kg",
      "today": "50.3kg",
      "total": "2,537.77kg"
    },
    "auctionAmount": {
      "untilYesterday": "570,202,157.5원",
      "today": "15,360,951원",
      "total": "585,563,108.5원"
    },
    "grade1": {
      "quantity": "0.21kg",
      "unitPrice": "666,600원"
    },
    "grade2": {
      "quantity": "0.57kg",
      "unitPrice": "646,600원"
    },
    "grade3Stopped": {
      "quantity": "2.37kg",
      "unitPrice": "444,400원"
    },
    "grade3Estimated": {
      "quantity": "25.55kg",
      "unitPrice": "358,500원"
    },
    "gradeBelow": {
      "quantity": "3.5kg",
      "unitPrice": "343,000원"
    },
    "mixedGrade": {
      "quantity": "18.1kg",
      "unitPrice": "190,000원"
    }
  }
]